[{
    "src":"../assets/images/ic_share_status.png",
    "author":"陈苍苍11",
    "follow":"53228人关注",
    "text":"临近20C，当尼采这个狂人宣告上帝已死的时候，现代性才跃出了启蒙思想家的思想图纸，犹如鬼魅一般真正进入了大众民众的日常思想谱系，于是，形式繁多的现代性学说主宰了20C的大众意识形态，无                 论是虚无主义，存在主义，还是马克思主义等等都是现代性语境下的产物。但随着现代性在意识形态的统治地位不断扩张，现代性所引发的病理在21C也愈发彰显。"
},
{
    "src":"../assets/images/ic_share_status.png",
    "author":"陈苍苍22",
    "follow":"53228人关注",
    "text":"临近20C，当尼采这个狂人宣告上帝已死的时候，现代性才跃出了启蒙思想家的思想图纸，犹如鬼魅一般真正进入了大众民众的日常思想谱系，于是，形式繁多的现代性学说主宰了20C的大众意识形态，无                 论是虚无主义，存在主义，还是马克思主义等等都是现代性语境下的产物。但随着现代性在意识形态的统治地位不断扩张，现代性所引发的病理在21C也愈发彰显。"
}
]